dictionary/__init__.py
dictionary/dictionary.py
btbt_dictionary-3.0.2.dist-info/METADATA
btbt_dictionary-3.0.2.dist-info/WHEEL
btbt_dictionary-3.0.2.dist-info/top_level.txt
btbt_dictionary-3.0.2.dist-info/RECORD
